netconf/__init__.py
netconf/__main__.py
netconf/base.py
netconf/client.py
netconf/error.py
netconf/server.py
netconf/util.py
netconf-2.1.0.dist-info/AUTHORS
netconf-2.1.0.dist-info/METADATA
netconf-2.1.0.dist-info/WHEEL
netconf-2.1.0.dist-info/entry_points.txt
netconf-2.1.0.dist-info/pbr.json
netconf-2.1.0.dist-info/top_level.txt
netconf-2.1.0.dist-info/RECORD
