Metadata-Version: 1.0
Name: netconf
Version: 2.1.0
Summary: Netconf server and client library.
Home-page: https://github.com/choppsv1/netconf/
Author: Christian Hopps
Author-email: chopps@gmail.com
License: Apache-2
Platform: UNKNOWN
